polysome/__init__.py
polysome/cli.py
polysome/execution_optimizer.py
polysome/prompt_editor.py
polysome/prompt_formatter.py
polysome/workflow.py
polysome/engines/__init__.py
polysome/engines/base.py
polysome/engines/engine_pool.py
polysome/engines/huggingface.py
polysome/engines/llama.py
polysome/engines/registry.py
polysome/engines/vllm.py
polysome/engines/vllm_dp.py
polysome/nodes/__init__.py
polysome/nodes/combine_outputs_node.py
polysome/nodes/jsonl_processing_node.py
polysome/nodes/load_node.py
polysome/nodes/node.py
polysome/nodes/node_registry.py
polysome/nodes/text_prompt_node.py
polysome/nodes/util_nodes.py
polysome/templates/prompts/simple_qa/few_shot.jsonl
polysome/templates/prompts/simple_qa/system_prompt.txt
polysome/templates/prompts/simple_qa/user_prompt.txt
polysome/templates/workflows/basic_text_generation.json
polysome/utils/__init__.py
polysome/utils/csv_writer.py
polysome/utils/data_loader.py
polysome/utils/json_parsing_pipeline.py
polysome/utils/jsonl_writer.py
polysome/utils/logging.py
polysome/utils/output_formatter.py
polysome/utils/post_processing.py
polysome/utils/tree_utils.py
polysome-0.1.1.dist-info/licenses/LICENSE
polysome-0.1.1.dist-info/METADATA
polysome-0.1.1.dist-info/WHEEL
polysome-0.1.1.dist-info/entry_points.txt
polysome-0.1.1.dist-info/top_level.txt
polysome-0.1.1.dist-info/RECORD
