Metadata-Version: 2.4
Name: polysome
Version: 0.1.1
Summary: A domain-agnostic framework for orchestrating LLM-based data generation workflows
Author-email: Sander Moonemans <sander.moonemans@radboudumc.nl>
License: MIT
Project-URL: Homepage, https://github.com/computationalpathologygroup/Polysome
Project-URL: Repository, https://github.com/computationalpathologygroup/Polysome
Project-URL: Issues, https://github.com/computationalpathologygroup/Polysome/issues
Keywords: llm,data-generation,machine-learning,workflow,instruction-tuning
Classifier: Programming Language :: Python :: 3
Classifier: Programming Language :: Python :: 3.10
Classifier: Programming Language :: Python :: 3.11
Classifier: Programming Language :: Python :: 3.12
Classifier: License :: OSI Approved :: MIT License
Classifier: Operating System :: OS Independent
Classifier: Development Status :: 4 - Beta
Classifier: Intended Audience :: Science/Research
Classifier: Topic :: Scientific/Engineering :: Artificial Intelligence
Requires-Python: >=3.10
License-File: LICENSE
Requires-Dist: python-dotenv
Requires-Dist: pandas==2.2.3
Requires-Dist: pandas-stubs==2.2.3.250308
Requires-Dist: openpyxl==3.1.5
Requires-Dist: transformers==4.51.3
Requires-Dist: torch>=2.0.0
Requires-Dist: accelerate>=0.26.0
Requires-Dist: jinja2>=3.0.0
Requires-Dist: tqdm>=4.65.0
Provides-Extra: dev
Requires-Dist: pytest==8.3.5; extra == "dev"
Requires-Dist: pytest-mock==3.14.0; extra == "dev"
Requires-Dist: pytest-cov>=4.0.0; extra == "dev"
Requires-Dist: pytest-xdist>=3.0.0; extra == "dev"
Provides-Extra: ui
Requires-Dist: streamlit; extra == "ui"
Provides-Extra: vllm
Requires-Dist: vllm>=0.8.0; platform_system == "Linux" and extra == "vllm"
Provides-Extra: llama-cpp
Requires-Dist: llama-cpp-python>=0.2.0; extra == "llama-cpp"
Provides-Extra: gpu
Requires-Dist: polysome[vllm]; extra == "gpu"
Provides-Extra: cpu
Requires-Dist: polysome[llama-cpp]; extra == "cpu"
Provides-Extra: gpu-dev
Requires-Dist: polysome[dev,gpu]; extra == "gpu-dev"
Provides-Extra: cpu-dev
Requires-Dist: polysome[cpu,dev]; extra == "cpu-dev"
Provides-Extra: all
Requires-Dist: polysome[dev,llama-cpp,ui,vllm]; extra == "all"
Dynamic: license-file
